flaskoidc_pp/__init__.py
flaskoidc_pp/config.py
flaskoidc_pp/store.py
flaskoidc_pp-0.0.10.dist-info/LICENSE
flaskoidc_pp-0.0.10.dist-info/METADATA
flaskoidc_pp-0.0.10.dist-info/WHEEL
flaskoidc_pp-0.0.10.dist-info/top_level.txt
flaskoidc_pp-0.0.10.dist-info/RECORD
