Metadata-Version: 2.1
Name: flaskoidc-pp
Version: 0.0.10
Summary: Flask wrapper with pre-configured OIDC support
Home-page: https://github.com/verdan/flaskoidc.git
Author: Verdan Mahmood
Author-email: verdan.mahmood@gmail.com
License: UNKNOWN
Platform: UNKNOWN
Requires-Python: >=3.6
Requires-Dist: FLASK
Requires-Dist: flask-oidc-pp
Requires-Dist: flask-sqlalchemy
Requires-Dist: flask-session
